{
  "title": "20111125_113212.jpg",
  "description": "20111125_113212.jpg",
  "imageViews": "0",
  "creationTime": {
    "timestamp": "1322217359",
    "formatted": "Nov 25, 2011, 10:35:59 AM UTC"
  },
  "modificationTime": {
    "timestamp": "1578215909",
    "formatted": "Jan 5, 2020, 9:18:29 AM UTC"
  },
  "geoData": {
    "latitude": 0.0,
    "longitude": 0.0,
    "altitude": 0.0,
    "latitudeSpan": 0.0,
    "longitudeSpan": 0.0
  },
  "geoDataExif": {
    "latitude": 0.0,
    "longitude": 0.0,
    "altitude": 0.0,
    "latitudeSpan": 0.0,
    "longitudeSpan": 0.0
  },
  "photoTakenTime": {
    "timestamp": "1322217132",
    "formatted": "Nov 25, 2011, 10:32:12 AM UTC"
  }
}